adsb/__init__.py
adsb/constants.py
adsb/mypy_types.py
adsb/utils.py
adsb/sbs/__init__.py
adsb/sbs/aircraft.py
adsb/sbs/archive.py
adsb/sbs/client.py
adsb/sbs/json_utils.py
adsb/sbs/message.py
adsb/sbs/protocol.py
adsb/sbs/server.py
adsb/sbs/session.py
adsb-0.0.1.dist-info/DESCRIPTION.rst
adsb-0.0.1.dist-info/METADATA
adsb-0.0.1.dist-info/RECORD
adsb-0.0.1.dist-info/WHEEL
adsb-0.0.1.dist-info/metadata.json
adsb-0.0.1.dist-info/top_level.txt
