Metadata-Version: 2.0
Name: adsb
Version: 0.0.1
Summary: ADS-B tools for Python
Home-page: https://github.com/claws/adsb
Author: Chris Laws
Author-email: clawsicus@gmail.com
License: MIT license
Keywords: adsb
Platform: UNKNOWN
Classifier: Development Status :: 3 - Alpha
Classifier: Intended Audience :: Developers
Classifier: Programming Language :: Python :: 3.6
Requires-Dist: quart
